cachetic/VERSION
cachetic/__init__.py
cachetic/extensions/__init__.py
cachetic/extensions/compression.py
cachetic/extensions/mongodb.py
cachetic/types/__init__.py
cachetic/types/cache_protocol.py
cachetic/types/document_param.py
cachetic/utils/__init__.py
cachetic/utils/compression.py
cachetic/utils/hide_url_password.py
cachetic-0.5.0.dist-info/METADATA
cachetic-0.5.0.dist-info/WHEEL
cachetic-0.5.0.dist-info/licenses/LICENSE
cachetic-0.5.0.dist-info/RECORD
