Metadata-Version: 2.4
Name: cachetic
Version: 0.5.0
Summary: Simple cache with pydantic.
License: MIT
License-File: LICENSE
Author: Allen Chou
Author-email: f1470891079@gmail.com
Requires-Python: >=3.11,<4
Classifier: License :: OSI Approved :: MIT License
Classifier: Programming Language :: Python :: 3
Classifier: Programming Language :: Python :: 3.11
Classifier: Programming Language :: Python :: 3.12
Classifier: Programming Language :: Python :: 3.13
Classifier: Programming Language :: Python :: 3.14
Provides-Extra: mongodb
Requires-Dist: diskcache (>=5)
Requires-Dist: pydantic (>=2,<3)
Requires-Dist: pydantic-settings
Requires-Dist: pymongo (>=4) ; extra == "mongodb"
Requires-Dist: redis (>=5)
Requires-Dist: rich
Requires-Dist: str_or_none
